pymug/__init__.py
pymug/__main__.py
pymug-1.5.0.dist-info/METADATA
pymug-1.5.0.dist-info/WHEEL
pymug-1.5.0.dist-info/entry_points.txt
pymug-1.5.0.dist-info/top_level.txt
pymug-1.5.0.dist-info/RECORD
