Metadata-Version: 2.1
Name: pymug
Version: 1.5.0
Summary: A Pymug Joke
Home-page: https://github.com/pymug
Author: Abdur-Rahmaan Janhangeer
Author-email: arj.python@gmail.com
License: MIT
Platform: UNKNOWN
Classifier: License :: OSI Approved :: MIT License
Classifier: Programming Language :: Python
Classifier: Programming Language :: Python :: 2
Classifier: Programming Language :: Python :: 3
